tbreader/__init__.py
tbreader/proto/__init__.py
tbreader/proto/event.proto
tbreader/proto/event_pb2.py
tbreader/proto/resource_handle.proto
tbreader/proto/resource_handle_pb2.py
tbreader/proto/summary.proto
tbreader/proto/summary_pb2.py
tbreader/proto/tensor.proto
tbreader/proto/tensor_pb2.py
tbreader/proto/tensor_shape.proto
tbreader/proto/tensor_shape_pb2.py
tbreader/proto/types.proto
tbreader/proto/types_pb2.py
tbreader/record_reader.py
tbreader/summary_reader.py
tbreader-1.0.1.dist-info/LICENSE
tbreader-1.0.1.dist-info/WHEEL
tbreader-1.0.1.dist-info/METADATA
tbreader-1.0.1.dist-info/RECORD
